editax/__init__.py
editax/learning.py
editax/moed.py
editax/policy/__init__.py
editax/policy/lstm.py
editax/template.py
editax/upomdp.py
editax/utils.py
editax-0.2.1.dist-info/LICENSE
editax-0.2.1.dist-info/METADATA
editax-0.2.1.dist-info/WHEEL
editax-0.2.1.dist-info/RECORD
