Metadata-Version: 2.1
Name: editax
Version: 0.2.1
Summary: Automatically created RL Environment Editors
License: Apache 2.0
Author: Rundong Liu
Author-email: rundong.liu@proton.me
Requires-Python: >=3.12,<4.0
Classifier: License :: Other/Proprietary License
Classifier: Programming Language :: Python :: 3
Classifier: Programming Language :: Python :: 3.12
Requires-Dist: chex (>=0.1.88,<0.2.0)
Requires-Dist: craftax (>=1.4.5,<2.0.0)
Requires-Dist: distrax (>=0.1.5,<0.2.0)
Requires-Dist: flax (>=0.10.3,<0.11.0)
Requires-Dist: gymnax (>=0.0.8,<0.0.9)
Requires-Dist: imageio (>=2.36.1,<3.0.0)
Requires-Dist: jax (>=0.5.0,<0.6.0)
Requires-Dist: jax2d (>=1.0.1,<2.0.0)
Requires-Dist: jaxgl (>=1.0.1,<2.0.0)
Requires-Dist: jaxlib (>=0.5.0,<0.6.0)
Requires-Dist: langchain (>=0.3.19,<0.4.0)
Requires-Dist: langchain-anthropic (>=0.3.7,<0.4.0)
Requires-Dist: langchain-openai (>=0.3.6,<0.4.0)
Requires-Dist: matplotlib (>=3.10.0,<4.0.0)
Requires-Dist: omegaconf (>=2.3.0,<3.0.0)
Requires-Dist: packaging (>=24.2,<25.0)
Requires-Dist: pygame (>=2.6.1,<3.0.0)
Requires-Dist: safetensors (>=0.5.2,<0.6.0)
